skillcorner_on_demand/__init__.py
skillcorner_on_demand/client.py
skillcorner_on_demand/method.py
skillcorner_on_demand-0.1.15.dist-info/METADATA
skillcorner_on_demand-0.1.15.dist-info/WHEEL
skillcorner_on_demand-0.1.15.dist-info/licenses/LICENCE.md
skillcorner_on_demand-0.1.15.dist-info/RECORD
