Metadata-Version: 2.4
Name: skillcorner-on-demand
Version: 0.1.15
Summary: Python client to interact with SkillCorner On Demand API
Author-email: SkillCorner <support@skillcorner.com>
License-File: LICENCE.md
Requires-Python: <3.13,>=3.9
Requires-Dist: fitrequest==0.8.2
Requires-Dist: requests>=2.32.3
